BioImageSuiteLite/__init__.py
BioImageSuiteLite/analysis_processor.py
BioImageSuiteLite/gui_manager.py
BioImageSuiteLite/io_operations.py
BioImageSuiteLite/roi_handler.py
BioImageSuiteLite/utilities.py
bioimagesuitelite-0.1.4.dist-info/licenses/LICENSE
bioimagesuitelite-0.1.4.dist-info/METADATA
bioimagesuitelite-0.1.4.dist-info/WHEEL
bioimagesuitelite-0.1.4.dist-info/entry_points.txt
bioimagesuitelite-0.1.4.dist-info/top_level.txt
bioimagesuitelite-0.1.4.dist-info/RECORD
