Metadata-Version: 2.4
Name: BioImageSuiteLite
Version: 0.1.4
Summary: A Python-based GUI tool for cellular event detection from .avi and .tiff files.
Author-email: Rinki Dasgupta <rinkidsgpt@gmail.com>, Kaushik Das <kaushik.k.das@gmail.com>
Project-URL: Homepage, https://github.com/InnovationLine/BioImageSuiteLite
Project-URL: Bug Tracker, https://github.com/InnovationLine/BioImageSuiteLite/issues
Classifier: Programming Language :: Python :: 3
Classifier: License :: OSI Approved :: MIT License
Classifier: Operating System :: OS Independent
Classifier: Development Status :: 3 - Alpha
Classifier: Intended Audience :: Science/Research
Classifier: Topic :: Scientific/Engineering :: Image Processing
Requires-Python: >=3.8
License-File: LICENSE
Requires-Dist: numpy
Requires-Dist: scipy
Requires-Dist: opencv-python-headless
Requires-Dist: tifffile
Requires-Dist: scikit-image
Requires-Dist: napari[all]
Requires-Dist: shapely
Requires-Dist: ruptures
Requires-Dist: matplotlib
Dynamic: license-file
